devpulse/__init__.py
devpulse/cli.py
devpulse/helper.py
devpulse/watcher.py
devpulse-0.1.0.dist-info/METADATA
devpulse-0.1.0.dist-info/WHEEL
devpulse-0.1.0.dist-info/entry_points.txt
devpulse-0.1.0.dist-info/top_level.txt
devpulse-0.1.0.dist-info/RECORD
